pkg_utils/__init__.py
pkg_utils/_version.py
pkg_utils/core.py
pkg_utils-0.0.5.dist-info/LICENSE
pkg_utils-0.0.5.dist-info/METADATA
pkg_utils-0.0.5.dist-info/WHEEL
pkg_utils-0.0.5.dist-info/top_level.txt
pkg_utils-0.0.5.dist-info/RECORD
